offline_folium/__init__.py
offline_folium/__main__.py
offline_folium/offline.py
offline_folium/paths.py
offline_folium-0.1.2.dist-info/LICENSE
offline_folium-0.1.2.dist-info/METADATA
offline_folium-0.1.2.dist-info/WHEEL
offline_folium-0.1.2.dist-info/top_level.txt
offline_folium-0.1.2.dist-info/RECORD
